[
    {
        "name": "Igor",
        "text": "Hi!",
        "date": "2018-03-22 18:00:00"
    },
    {
        "name": "Jane",
        "text": "Hi! What is your name?",
        "date": "2018-03-22 18:01:00"
    },
    {
        "name": "Igor",
        "text": "My name is Igor",
        "date": "2018-03-22 18:01:45"
    },
    {
        "name": "Jane",
        "text": "Good, my name is Jane!",
        "date": "2018-03-22 18:02:53"
    },
    {
        "name": "Jane",
        "text": "Nice to meet you!",
        "date": "2018-03-22 18:03:17"
    },
    {
        "name": "Igor",
        "text": "Nice to meet you too!",
        "date": "2018-03-22 18:04:25"
    },
    {
        "name": "Vlad",
        "text": "asfafadgdsgSDGSDGrGS gr",
        "date": "2018-03-22 11:21:12"
    },
    {
        "name": "Jane",
        "text": "asfasfasfg",
        "date": "2018-03-22 11:21:22"
    },
    {
        "name": "Igor",
        "text": "sad",
        "date": "2018-03-22 11:22:26"
    },
    {
        "name": "Vlad",
        "text": "asfasfasgaewg",
        "date": "2018-03-22 11:23:44"
    },
    {
        "name": "Vasya",
        "text": "adgsegjhrg",
        "date": "2018-03-22 11:23:51"
    },
    {
        "name": "Gena",
        "text": "asfasfga",
        "date": "2018-03-22 11:24:23"
    },
    {
        "name": "Gena",
        "text": "asfasfga",
        "date": "2018-03-22 11:24:33"
    },
    {
        "name": "Igor",
        "text": "Proverka",
        "date": "2018-03-22 11:31:05"
    },
    {
        "name": "Igor",
        "text": "Proverka2",
        "date": "2018-03-22 11:31:45"
    },
    {
        "name": "Igor",
        "text": "asdasf",
        "date": "2018-03-22 11:38:42"
    },
    {
        "name": "fafas",
        "text": "afsga",
        "date": "2018-03-22 11:38:45"
    }
]